wotd/WordOfTheDay.py
wotd/__init__.py
wordoftheday-0.0.1.dist-info/LICENSE
wordoftheday-0.0.1.dist-info/METADATA
wordoftheday-0.0.1.dist-info/WHEEL
wordoftheday-0.0.1.dist-info/top_level.txt
wordoftheday-0.0.1.dist-info/RECORD
