Metadata-Version: 2.1
Name: wordoftheday
Version: 0.0.1
Summary: get the word of the day from various sources
Home-page: https://github.com/patrickc-dev/wordoftheday
Author: Patrick C
Author-email: 52078333+patrickc-dev@users.noreply.github.com
License: UNKNOWN
Platform: UNKNOWN
Classifier: Programming Language :: Python :: 3
Classifier: License :: OSI Approved :: MIT License
Classifier: Operating System :: OS Independent
Requires-Python: >=3.6
Requires-Dist: requests
Requires-Dist: beautifulsoup4
